MANIFEST.in
README.md
setup.cfg
setup.py
ADPY/__init__.py
ADPY.egg-info/PKG-INFO
ADPY.egg-info/SOURCES.txt
ADPY.egg-info/dependency_links.txt
ADPY.egg-info/top_level.txt
ADPY/ADFUN/__init__.py
ADPY/ADFUN/adfloat.py
ADPY/ADFUN/adfun.py
ADPY/ADFUN/globalfuncs.py
ADPY/ADFUN/library.py
ADPY/SOLVER/__init__.py
ADPY/SOLVER/solver.py