Metadata-Version: 1.1
Name: ADPY
Version: 0.12.alpha
Summary: ADPY is a Python library for algorithmic differentiation
Home-page: https://github.com/zwenson/ADPY
Author: Oliver Schnabel
Author-email: zwenson@rocketmail.com
License: GPLv3
Keywords: python algorithmic differentiation scientific numpy
Platform: UNKNOWN
Classifier: Development Status :: 3 - Alpha
Classifier: Programming Language :: Python :: 2.7
Classifier: Intended Audience :: Science/Research
Classifier: Topic :: Scientific/Engineering :: Mathematics
Classifier: License :: OSI Approved :: GNU General Public License v3 or later (GPLv3+)
